{
  "version": 1,
  "updatedAt": "2026-04-28T23:32:23.221Z",
  "plugins": [
    {
      "id": "youtube-link-cleaner",
      "name": "YouTube Link Cleaner",
      "version": "0.1.2",
      "author": "@jj1guj",
      "description": "投稿時に YouTube URL の追跡クエリを自動削除",
      "category": "posting",
      "tags": [
        "youtube",
        "url",
        "cleanup"
      ],
      "sourceUrl": "https://misstore.hital.in/registry/plugins/youtube-link-cleaner/plugin.is",
      "apiUrl": "https://misstore.hital.in/registry/plugins/youtube-link-cleaner/api.json",
      "sha512": "128cdc9b717019ddc4aec84cce788d7be84e480d78f5f5b6cfb70d0d43005195d138f16e20c640ac216466f772a43f49db5b3c6dfd4e2138d19585e404b54efd",
      "createdAt": "2026-04-28T23:32:23.223Z",
      "updatedAt": "2026-04-28T23:32:23.223Z",
      "authorUrl": "https://github.com/jj1guj",
      "license": "MIT",
      "repository": "https://github.com/jj1guj/misskey_youtube_link_cleaner",
      "iconUrl": "https://misstore.hital.in/registry/plugins/youtube-link-cleaner/icon.svg"
    }
  ]
}
